ourcompose/__init__.py
ourcompose/framework.py
ourcompose/mini.py
ourcompose-0.0.10.dist-info/LICENSE
ourcompose-0.0.10.dist-info/METADATA
ourcompose-0.0.10.dist-info/WHEEL
ourcompose-0.0.10.dist-info/RECORD
