Metadata-Version: 2.1
Name: ourcompose
Version: 0.0.10
Summary: Framework for setup and running functions (asynchronously) in topological order
Author: Rikard Olsson
Author-email: rikard@ourstudio.se
Requires-Python: >=3.8,<4.0
Classifier: Programming Language :: Python :: 3
Classifier: Programming Language :: Python :: 3.8
Classifier: Programming Language :: Python :: 3.9
Classifier: Programming Language :: Python :: 3.10
Classifier: Programming Language :: Python :: 3.11
Classifier: Programming Language :: Python :: 3.12
Requires-Dist: toposort (>=1.6,<2.0)
